Vectoryx/Vectoryx.py
Vectoryx/__init__.py
vectoryx-0.2.2.dist-info/licenses/LICENSE
vectoryx-0.2.2.dist-info/METADATA
vectoryx-0.2.2.dist-info/WHEEL
vectoryx-0.2.2.dist-info/top_level.txt
vectoryx-0.2.2.dist-info/RECORD
