Metadata-Version: 2.4
Name: Vectoryx
Version: 0.2.2
Summary: A simple vector operations library
Home-page: https://github.com/ArtemK2007/Vectoryx
Author: Artem Kryachko
Author-email: artemkryachko2007@email.com
Classifier: Programming Language :: Python :: 3
Classifier: License :: OSI Approved :: MIT License
Requires-Python: >=3.6
License-File: LICENSE
Dynamic: author
Dynamic: author-email
Dynamic: classifier
Dynamic: description
Dynamic: description-content-type
Dynamic: home-page
Dynamic: license-file
Dynamic: requires-python
Dynamic: summary
